README.rst
setup.py
celeryman/__init__.py
celeryman/admin.py
celeryman/apps.py
celeryman/exceptions.py
celeryman/models.py
celeryman/tasks.py
celeryman/tests.py
celeryman/utils.py
celeryman/validators.py
celeryman/views.py
celeryman.egg-info/PKG-INFO
celeryman.egg-info/SOURCES.txt
celeryman.egg-info/dependency_links.txt
celeryman.egg-info/requires.txt
celeryman.egg-info/top_level.txt